pingscope/__init__.py
pingscope/cli.py
pingscope/pingscope.py
pingscope-0.1.6.dist-info/LICENSE
pingscope-0.1.6.dist-info/METADATA
pingscope-0.1.6.dist-info/WHEEL
pingscope-0.1.6.dist-info/entry_points.txt
pingscope-0.1.6.dist-info/top_level.txt
pingscope-0.1.6.dist-info/RECORD
